LICENSE
MANIFEST.in
README.md
setup.cfg
setup.py
pinyin_tone_converter/__init__.py
pinyin_tone_converter/pinyin_tone_converter.py
pinyin_tone_converter/util.py
pinyin_tone_converter.egg-info/PKG-INFO
pinyin_tone_converter.egg-info/SOURCES.txt
pinyin_tone_converter.egg-info/dependency_links.txt
pinyin_tone_converter.egg-info/requires.txt
pinyin_tone_converter.egg-info/top_level.txt
tests/__init__.py
tests/test_converter.py