Metadata-Version: 2.1
Name: pinyin-tone-converter
Version: 1.0.2
Summary: Numbered pinyin to accented pinyin converter
Home-page: https://github.com/Lingyuai/pinyin-tone-converter
Author: Lingyuai
Author-email: developers@lingyuai.com
License: UNKNOWN
Download-URL: https://github.com/Lingyuai/pinyin-tone-converter/archive/1.0.2.tar.gz
Keywords: python,pinyin,pinyin-tone-converter,tones,numbered tones,marked tones,accented tones,chinese
Platform: UNKNOWN
Classifier: Development Status :: 4 - Beta
Classifier: Intended Audience :: Developers
Classifier: License :: OSI Approved :: MIT License
Classifier: Programming Language :: Python :: 3
Classifier: Operating System :: MacOS :: MacOS X
Classifier: Operating System :: Microsoft :: Windows
Classifier: Operating System :: POSIX
Provides-Extra: dev
Provides-Extra: dev-test
